MANIFEST.in
changes.txt
license.txt
readme.md
setup.py
nive_cms_design_bs_grayscale/__init__.py
nive_cms_design_bs_grayscale/view.py
nive_cms_design_bs_grayscale.egg-info/PKG-INFO
nive_cms_design_bs_grayscale.egg-info/SOURCES.txt
nive_cms_design_bs_grayscale.egg-info/dependency_links.txt
nive_cms_design_bs_grayscale.egg-info/not-zip-safe
nive_cms_design_bs_grayscale.egg-info/requires.txt
nive_cms_design_bs_grayscale.egg-info/top_level.txt
nive_cms_design_bs_grayscale/static/styles.css
nive_cms_design_bs_grayscale/static/css/bootstrap.css
nive_cms_design_bs_grayscale/static/css/bootstrap.min.css
nive_cms_design_bs_grayscale/static/css/grayscale.css
nive_cms_design_bs_grayscale/static/font-awesome-4.1.0/css/font-awesome.css
nive_cms_design_bs_grayscale/static/font-awesome-4.1.0/css/font-awesome.min.css
nive_cms_design_bs_grayscale/static/font-awesome-4.1.0/fonts/FontAwesome.otf
nive_cms_design_bs_grayscale/static/font-awesome-4.1.0/fonts/fontawesome-webfont.eot
nive_cms_design_bs_grayscale/static/font-awesome-4.1.0/fonts/fontawesome-webfont.svg
nive_cms_design_bs_grayscale/static/font-awesome-4.1.0/fonts/fontawesome-webfont.ttf
nive_cms_design_bs_grayscale/static/font-awesome-4.1.0/fonts/fontawesome-webfont.woff
nive_cms_design_bs_grayscale/static/font-awesome-4.1.0/less/bordered-pulled.less
nive_cms_design_bs_grayscale/static/font-awesome-4.1.0/less/core.less
nive_cms_design_bs_grayscale/static/font-awesome-4.1.0/less/fixed-width.less
nive_cms_design_bs_grayscale/static/font-awesome-4.1.0/less/font-awesome.less
nive_cms_design_bs_grayscale/static/font-awesome-4.1.0/less/icons.less
nive_cms_design_bs_grayscale/static/font-awesome-4.1.0/less/larger.less
nive_cms_design_bs_grayscale/static/font-awesome-4.1.0/less/list.less
nive_cms_design_bs_grayscale/static/font-awesome-4.1.0/less/mixins.less
nive_cms_design_bs_grayscale/static/font-awesome-4.1.0/less/path.less
nive_cms_design_bs_grayscale/static/font-awesome-4.1.0/less/rotated-flipped.less
nive_cms_design_bs_grayscale/static/font-awesome-4.1.0/less/spinning.less
nive_cms_design_bs_grayscale/static/font-awesome-4.1.0/less/stacked.less
nive_cms_design_bs_grayscale/static/font-awesome-4.1.0/less/variables.less
nive_cms_design_bs_grayscale/static/font-awesome-4.1.0/scss/_bordered-pulled.scss
